.gitignore
CHANGES.rst
MANIFEST.in
README.rst
README.txt
setup.py
xm.theme-configure.zcml
docs/INSTALL.txt
docs/LICENSE.GPL
docs/LICENSE.txt
xm/__init__.py
xm.theme.egg-info/PKG-INFO
xm.theme.egg-info/SOURCES.txt
xm.theme.egg-info/dependency_links.txt
xm.theme.egg-info/entry_points.txt
xm.theme.egg-info/namespace_packages.txt
xm.theme.egg-info/not-zip-safe
xm.theme.egg-info/requires.txt
xm.theme.egg-info/top_level.txt
xm/theme/__init__.py
xm/theme/configure.zcml
xm/theme/profiles.zcml
xm/theme/rebuild_i18n.sh
xm/theme/setuphandlers.py
xm/theme/skins.zcml
xm/theme/tests.py
xm/theme/browser/__init__.py
xm/theme/browser/configure.zcml
xm/theme/browser/interfaces.py
xm/theme/browser/project.py
xm/theme/browser/project_list.py
xm/theme/browser/viewlets.py
xm/theme/browser/stylesheets/README.txt
xm/theme/browser/stylesheets/main.kss
xm/theme/browser/templates/contentviews.pt
xm/theme/browser/templates/dashboard.pt
xm/theme/browser/templates/googlesearch.pt
xm/theme/browser/templates/login.pt
xm/theme/browser/templates/manage-dashboard.pt
xm/theme/browser/templates/my_projects.pt
xm/theme/browser/templates/my_projects_stub.pt
xm/theme/browser/templates/path_bar.pt
xm/theme/browser/templates/personal_bar.pt
xm/theme/browser/templates/project_content.pt
xm/theme/browser/templates/project_content_page.pt
xm/theme/browser/templates/project_header.pt
xm/theme/browser/templates/search.xml.dtml
xm/theme/browser/templates/searchbox.pt
xm/theme/locales/xm.theme.pot
xm/theme/locales/de/LC_MESSAGES/xm.theme.mo
xm/theme/locales/de/LC_MESSAGES/xm.theme.po
xm/theme/locales/en/LC_MESSAGES/xm.theme.mo
xm/theme/locales/en/LC_MESSAGES/xm.theme.po
xm/theme/locales/it/LC_MESSAGES/xm.theme.mo
xm/theme/locales/it/LC_MESSAGES/xm.theme.po
xm/theme/locales/nl/LC_MESSAGES/xm.theme.mo
xm/theme/locales/nl/LC_MESSAGES/xm.theme.po
xm/theme/mockup/logo xm - tryout 01.jpg
xm/theme/mockup/prototype dragable schedule v01.jpg
xm/theme/mockup/tracker - expand all tasks.jpg
xm/theme/mockup/xm - collapse all iterations.jpg
xm/theme/mockup/xm - expand all iterations.jpg
xm/theme/profiles/default/actions.xml
xm/theme/profiles/default/cssregistry.xml
xm/theme/profiles/default/import_steps.xml
xm/theme/profiles/default/jsregistry.xml
