Metadata-Version: 1.0
Name: xm.theme
Version: 1.3
Summary: Theme for eXtremeManagement
Home-page: http://zestsoftware.nl
Author: Zest Software
Author-email: info@zestsoftware.nl
License: GPL
Keywords: web zope plone theme
Platform: UNKNOWN
Classifier: Framework :: Plone
Classifier: Framework :: Zope2
Classifier: Framework :: Zope3
Classifier: Programming Language :: Python
Classifier: Topic :: Software Development :: Libraries :: Python Modules
